query_tool/__init__.py
query_tool/frontend/dist/index.html
query_tool/frontend/dist/vite.svg
query_tool/frontend/dist/assets/index-49ab9bc7.js
query_tool/frontend/dist/assets/index-99e5fe3f.js
query_tool/frontend/dist/assets/index-b14312ff.js
query_tool/frontend/dist/assets/index-d081bea5.css
query_tool/frontend/dist/assets/index-d72f7278.js
query_tool/services/__init__.py
query_tool/services/dimension_service.py
query_tool/services/entities_service.py
query_tool/services/filters_service.py
query_tool/services/query_tool_factory.py
query_tool/services/query_tool_service.py
query_tool/services/register.py
test_query_tool-0.3.7.dist-info/LICENSE
test_query_tool-0.3.7.dist-info/METADATA
test_query_tool-0.3.7.dist-info/WHEEL
test_query_tool-0.3.7.dist-info/top_level.txt
test_query_tool-0.3.7.dist-info/RECORD
