Metadata-Version: 2.1
Name: test-query-tool
Version: 0.3.7
Summary: Query tool to generate query from selection
Home-page: UNKNOWN
Author: Bluepinapple
Author-email: viveksthul@bluepinapple.com
License: UNKNOWN
Platform: UNKNOWN
Requires-Python: >=3.9.6
License-File: LICENSE
Requires-Dist: streamlit (>=1.20.0)
